r2x_reeds/__init__.py
r2x_reeds/config/commits.txt
r2x_reeds/config/defaults.json
r2x_reeds/config/exporter_rules.json
r2x_reeds/config/file_mapping.json
r2x_reeds/config/parser_rules.json
r2x_reeds/config/pcm_defaults.json
r2x_reeds/config/translation_rules.json
r2x_reeds/enum_mappings.py
r2x_reeds/getters.py
r2x_reeds/models/__init__.py
r2x_reeds/models/base.py
r2x_reeds/models/components.py
r2x_reeds/models/enums.py
r2x_reeds/models/units.py
r2x_reeds/parser.py
r2x_reeds/parser_checks.py
r2x_reeds/parser_types.py
r2x_reeds/parser_utils.py
r2x_reeds/plugin_config.py
r2x_reeds/plugins.py
r2x_reeds/py.typed
r2x_reeds/row_utils.py
r2x_reeds/rules_helper.py
r2x_reeds/sysmod/__init__.py
r2x_reeds/sysmod/break_gens.py
r2x_reeds/sysmod/ccs_credit.py
r2x_reeds/sysmod/electrolyzer.py
r2x_reeds/sysmod/emission_cap.py
r2x_reeds/sysmod/imports.py
r2x_reeds/sysmod/pcm_defaults.py
r2x_reeds/sysmod/utils.py
r2x_reeds/upgrader/__init__.py
r2x_reeds/upgrader/data_upgrader.py
r2x_reeds/upgrader/file_tracker.csv
r2x_reeds/upgrader/helpers.py
r2x_reeds/upgrader/upgrade_steps.py
r2x_reeds-0.3.4.dist-info/WHEEL
r2x_reeds-0.3.4.dist-info/entry_points.txt
r2x_reeds-0.3.4.dist-info/METADATA
r2x_reeds-0.3.4.dist-info/RECORD
